csv_converter_valtensir/__init__.py
csv_converter_valtensir/converter.py
csv_converter_valtensir-0.1.2.dist-info/entry_points.txt
csv_converter_valtensir-0.1.2.dist-info/WHEEL
csv_converter_valtensir-0.1.2.dist-info/METADATA
csv_converter_valtensir-0.1.2.dist-info/RECORD
