Metadata-Version: 2.1
Name: csv-converter-valtensir
Version: 0.1.2
Summary: A project to converter JSON to CSV and CSV to JSON files.
Author: Valtensir Lopes
Author-email: valtensirl@gmail.com
Requires-Python: >=3.8,<4.0
Classifier: Programming Language :: Python :: 3
Classifier: Programming Language :: Python :: 3.10
Classifier: Programming Language :: Python :: 3.8
Classifier: Programming Language :: Python :: 3.9
Requires-Dist: click (>=8.0.3,<9.0.0)
